ml_ephys/__init__.py
ml_ephys/basic/__init__.py
ml_ephys/basic/basic.py.mp
ml_ephys/basic/p_compute_cluster_metrics.py
ml_ephys/basic/p_compute_cross_correlograms.py
ml_ephys/basic/p_compute_templates.py
ml_ephys/basic/p_convert_array.py
ml_ephys/basic/timeserieschunkreader.py
ml_ephys/preprocessing/__init__.py
ml_ephys/preprocessing/p_bandpass_filter.py
ml_ephys/preprocessing/p_mask_out_artifacts.py
ml_ephys/preprocessing/p_whiten.py
ml_ephys/preprocessing/preprocessing.py.mp
ml_ephys/synthesis/__init__.py
ml_ephys/synthesis/p_synthesize_drifting_timeseries.py
ml_ephys/synthesis/p_synthesize_random_firings.py
ml_ephys/synthesis/p_synthesize_random_waveforms.py
ml_ephys/synthesis/p_synthesize_timeseries.py
ml_ephys/synthesis/synthesis.py.mp
ml_ephys/synthesis/synthesize_single_waveform.py
ml_ephys/validation/__init__.py
ml_ephys/validation/p_compare_ground_truth.py
ml_ephys/validation/validation.py.mp
ml_ephys-0.2.14.dist-info/LICENSE
ml_ephys-0.2.14.dist-info/METADATA
ml_ephys-0.2.14.dist-info/WHEEL
ml_ephys-0.2.14.dist-info/top_level.txt
ml_ephys-0.2.14.dist-info/RECORD
