Metadata-Version: 2.1
Name: ml-ephys
Version: 0.2.14
Summary: ephys tools for MountainLab
Home-page: https://github.com/magland/ml_ephys
Author: Jeremy Magland
Author-email: 
License: UNKNOWN
Platform: UNKNOWN
Classifier: Programming Language :: Python :: 3
Classifier: License :: OSI Approved :: Apache Software License
Classifier: Operating System :: OS Independent
Requires-Dist: numpy
Requires-Dist: mountainlab-pytools
Requires-Dist: deepdish
Requires-Dist: scipy
Requires-Dist: numpydoc
Requires-Dist: h5py
